AUTHORS.rst
DEVELOP.rst
MANIFEST.in
README.rst
mkchroot.sh
rmchroot.sh
setup.py
tox.ini
unittest.cfg
dirtbike/__init__.py
dirtbike/__main__.py
dirtbike/strategy.py
dirtbike.egg-info/PKG-INFO
dirtbike.egg-info/SOURCES.txt
dirtbike.egg-info/dependency_links.txt
dirtbike.egg-info/entry_points.txt
dirtbike.egg-info/requires.txt
dirtbike.egg-info/top_level.txt