Metadata-Version: 1.0
Name: dirtbike
Version: 0.2
Summary: Convert already-installed Python modules ("distribution") to wheel
Home-page: https://github.com/paulproteus/dirtbike
Author: Asheesh Laroia
Author-email: asheesh@asheesh.org
License: UNKNOWN
Platform: UNKNOWN
